jsonfromschema/__init__.py
jsonfromschema/cli.py
jsonfromschema/lib.py
tests/__init__.py
tests/test_main.py
jsonfromschema-0.1.4.dist-info/LICENSE
jsonfromschema-0.1.4.dist-info/METADATA
jsonfromschema-0.1.4.dist-info/WHEEL
jsonfromschema-0.1.4.dist-info/entry_points.txt
jsonfromschema-0.1.4.dist-info/top_level.txt
jsonfromschema-0.1.4.dist-info/RECORD
